bigbuild/__init__.py
bigbuild/apps.py
bigbuild/compressors.py
bigbuild/context_processors.py
bigbuild/exceptions.py
bigbuild/feeds.py
bigbuild/forms.py
bigbuild/precompilers.py
bigbuild/serializers.py
bigbuild/sitemaps.py
bigbuild/urls.py
bigbuild/views.py
bigbuild/management/__init__.py
bigbuild/management/commands/__init__.py
bigbuild/management/commands/archivepage.py
bigbuild/management/commands/build.py
bigbuild/management/commands/cachepages.py
bigbuild/management/commands/createpage.py
bigbuild/management/commands/publish.py
bigbuild/management/commands/testserializer.py
bigbuild/management/commands/unarchivepage.py
bigbuild/management/commands/validatepages.py
bigbuild/models/__init__.py
bigbuild/models/archivedpages.py
bigbuild/models/base.py
bigbuild/models/pagelists.py
bigbuild/models/pages.py
bigbuild/static/bigbuilder/example-big-build-metadata-edit.png
bigbuild/static/bigbuilder/example-big-build-metadata.png
bigbuild/static/bigbuilder/example-big-build-travis.png
bigbuild/static/bigbuilder/example-big-build.png
bigbuild/static/bigbuilder/favicon.ico
bigbuild/templates/bigbuild/404.html
bigbuild/templates/bigbuild/base.html
bigbuild/templates/bigbuild/google-news-sitemap.xml
bigbuild/templates/bigbuild/page_list.html
bigbuild/templates/bigbuild/robots.txt
bigbuild/templates/bigbuild/sitemap.xml
bigbuild/templates/bigbuild/pages/app.js-tpl
bigbuild/templates/bigbuild/pages/bigbar.html
bigbuild/templates/bigbuild/pages/checklist.md-tpl
bigbuild/templates/bigbuild/pages/default_index.html
bigbuild/templates/bigbuild/pages/style.css-tpl
bigbuild/templates/bigbuild/warnings/banner.txt
bigbuild/templates/bigbuild/warnings/bottom_border.txt
bigbuild/templates/bigbuild/warnings/footer.txt
bigbuild/templates/bigbuild/warnings/missing_metadata.txt
bigbuild/templates/bigbuild/warnings/missing_recommended_metadata.txt
bigbuild/templatetags/__init__.py
bigbuild/templatetags/bigbuild_tags.py
django_bigbuild-0.9.8.dist-info/LICENSE
django_bigbuild-0.9.8.dist-info/METADATA
django_bigbuild-0.9.8.dist-info/WHEEL
django_bigbuild-0.9.8.dist-info/top_level.txt
django_bigbuild-0.9.8.dist-info/RECORD
