Metadata-Version: 2.1
Name: django-bigbuild
Version: 0.9.8
Summary: The open-source engine that powers bigbuilder, the Los Angeles Times Data Desk's system for publishing standalone pages
Home-page: http://www.github.com/datadesk/django-bigbuild/
Author: The Los Angeles Times Data Desk
Author-email: datadesk@latimes.com
License: MIT
Platform: UNKNOWN
Classifier: Development Status :: 5 - Production/Stable
Classifier: Programming Language :: Python
Classifier: Programming Language :: Python :: 2
Classifier: Programming Language :: Python :: 2.7
Classifier: Programming Language :: Python :: 3
Classifier: Programming Language :: Python :: 3.5
Classifier: Programming Language :: Python :: 3.6
Classifier: Framework :: Django
Classifier: Framework :: Django :: 1.11
Classifier: License :: OSI Approved :: MIT License
Requires-Dist: python-frontmatter (>=0.4.2)
Requires-Dist: django-bakery (==0.12.5)
Requires-Dist: validictory (>=1.0.1)
Requires-Dist: django-compressor (==2.2)
Requires-Dist: django-compressor-toolkit (>=0.6.0)
Requires-Dist: greeking (>=2.2.0)
Requires-Dist: GitPython (>=2.0.8)
Requires-Dist: python-dateutil (>=2.6.0)
Requires-Dist: archieml (>=0.3.1)
Requires-Dist: django-jsonfield (>=1.0.1)
Requires-Dist: pytz
Requires-Dist: six
